Metadata-Version: 2.2
Name: mcp-server-software
Version: 0.1.0
Summary: A Model Context Protocol server that provides software management capabilities for your computer. 
Requires-Python: >=3.9
Requires-Dist: httpx>=0.28.1
Requires-Dist: mcp[cli]>=1.3.0
Requires-Dist: psutil>=7.0.0
Requires-Dist: pywin32>=309; sys_platform == "win32"
